vsgan/__init__.py
vsgan/archs/EGVSR.py
vsgan/archs/ESRGAN.py
vsgan/archs/__init__.py
vsgan/archs/blocks.py
vsgan/constants.py
vsgan/networks/__init__.py
vsgan/networks/basenetwork.py
vsgan/networks/egvsr.py
vsgan/networks/esrgan.py
vsgan/utilities.py
vsgan-1.6.4.dist-info/LICENSE
vsgan-1.6.4.dist-info/WHEEL
vsgan-1.6.4.dist-info/METADATA
vsgan-1.6.4.dist-info/RECORD
