Metadata-Version: 2.1
Name: vsgan
Version: 1.6.4
Summary: VapourSynth Single Image Super-Resolution Generative Adversarial Network (GAN)
Home-page: https://github.com/rlaphoenix/vsgan
License: MIT
Keywords: vapoursynth,upscaling,gan,deep-learning,esrgan
Author: PHOENiX
Author-email: rlaphoenix@pm.me
Requires-Python: >=3.7,<4.0
Classifier: Development Status :: 5 - Production/Stable
Classifier: Intended Audience :: Developers
Classifier: License :: OSI Approved :: MIT License
Classifier: Natural Language :: English
Classifier: Operating System :: OS Independent
Classifier: Programming Language :: Python :: 3
Classifier: Programming Language :: Python :: 3.10
Classifier: Programming Language :: Python :: 3.7
Classifier: Programming Language :: Python :: 3.8
Classifier: Programming Language :: Python :: 3.9
Classifier: Topic :: Multimedia :: Video
Provides-Extra: docs
Provides-Extra: pytorch
Provides-Extra: vs
Requires-Dist: Sphinx (>=4.3.2,<5.0.0); extra == "docs"
Requires-Dist: VapourSynth (>=57,<58); extra == "vs"
Requires-Dist: dunamai (>=1.7.0,<2.0.0); extra == "docs"
Requires-Dist: furo (>=2021.11.23,<2022.0.0); extra == "docs"
Requires-Dist: m2r2 (>=0.3.2,<0.4.0); extra == "docs"
Requires-Dist: numpy (>=1.21.1,<2.0.0)
Requires-Dist: sphinxcontrib-images (>=0.9.4,<0.10.0); extra == "docs"
Requires-Dist: sphinxcontrib-youtube (>=1.0.1,<2.0.0); extra == "docs"
Requires-Dist: torch (>=1.10.0,<2.0.0); extra == "pytorch"
Project-URL: Repository, https://github.com/rlaphoenix/vsgan
